{
  "patches_lines": 1469,
  "iife_blocks": [
    {
      "start": 25,
      "end": 650,
      "lines": 626,
      "guard": "__BACK_CTRL__",
      "head": "(function(){ 'use strict'; if(window.__BACK_CTRL__) return; window.__BACK_CTRL__ = true; window.__OAI_FULL_BACK_CTRL_ACTIVE__ = true; var _href = location.href.split('#')[0]; funct"
    },
    {
      "start": 651,
      "end": 674,
      "lines": 24,
      "guard": "__APP_PRAYER_VIEW_HELPER__",
      "head": "자동 ?v=Date.now 리디렉션은 사용하지 않음: 버전 문자열과 서비스워커로 캐시를 관리 시작 시 강제 상태 초기화는 사용하지 않음: 뒤로가기와 외부사이트 복귀 상태 보존 (function(){ 'use strict'; if(window.__APP_PRAYER_VIEW_HELPER__) return; window.__"
    },
    {
      "start": 675,
      "end": 705,
      "lines": 31,
      "guard": "__APP_PRAYER_SYNC_GUARD__",
      "head": "})(); (function(){ if(window.__APP_PRAYER_SYNC_GUARD__) return; window.__APP_PRAYER_SYNC_GUARD__ = true; function syncPrayerTabOn(){ var wrap = document.getElementById('prayer-tabs"
    },
    {
      "start": 706,
      "end": 724,
      "lines": 19,
      "guard": "",
      "head": "}, true); document.addEventListener('DOMContentLoaded', function(){ setTimeout(syncPrayerTabOn, 300); }); window.addEventListener('load', function(){ setTimeout(syncPrayerTabOn, 30"
    },
    {
      "start": 725,
      "end": 772,
      "lines": 48,
      "guard": "__APP_FAITH_GUARD__",
      "head": "}).observe(pv, {attributes:true, attributeFilter:['class']}); })(); })(); (function(){ if(window.__APP_FAITH_GUARD__) return; window.__APP_FAITH_GUARD__ = true; function normalizeP"
    },
    {
      "start": 773,
      "end": 872,
      "lines": 100,
      "guard": "__APP_FONT_SCALE_GUARD__",
      "head": "(function(){ if(window.__APP_FONT_SCALE_GUARD__) return; window.__APP_FONT_SCALE_GUARD__=true; V3-13: 커버 글자 크기 조절은 prayer.js에 의존하지 않는 공통 함수가 담당한다. prayer.js는 기도문 화면이 열렸을 때 같은 local"
    },
    {
      "start": 873,
      "end": 936,
      "lines": 64,
      "guard": "__APP_PWA_INSTALL_GUARD__",
      "head": "})(); user-cache mode: keep app cache stable; refresh changed files through versioned URLs. ── PWA 설치 버튼 로직 ── (function(){ PWA 설치 버튼 통합 컨트롤러 ① standalone(설치된 앱) 상태이면 버튼 즉시 숨기고 종료 "
    },
    {
      "start": 937,
      "end": 964,
      "lines": 28,
      "guard": "",
      "head": "window.addEventListener('load', applyVisibility); window.addEventListener('pageshow', applyVisibility); })(); ====== 성능 최적화 보정 ====== (function(){ 화면 전환 중 불필요한 레이아웃 부담을 줄인다. cover의"
    },
    {
      "start": 965,
      "end": 1084,
      "lines": 120,
      "guard": "__APP_BACK_ROUTE_GUARD__",
      "head": "if(el) observer.observe(el, {attributes:true, attributeFilter:['class']}); }); })(); (function(){ 'use strict'; if(window.__APP_BACK_ROUTE_GUARD__) return; window.__APP_BACK_ROUTE_"
    },
    {
      "start": 1085,
      "end": 1097,
      "lines": 13,
      "guard": "__APP_PRECISE_GUARD__",
      "head": "} if(document.readyState==='loading') document.addEventListener('DOMContentLoaded', init); else init(); window.addEventListener('load', init); window.addEventListener('pageshow', i"
    },
    {
      "start": 1098,
      "end": 1117,
      "lines": 20,
      "guard": "",
      "head": "function restoreDest(dest){ if(!dest||!dest.lat) return; setTimeout(function(){ try{ var items=(typeof _getCurrentItems==='function')?_getCurrentItems():[]; var idx=(typeof dest.id"
    },
    {
      "start": 1118,
      "end": 1123,
      "lines": 6,
      "guard": "",
      "head": "ov.classList.add('active'); clearTimeout(ov._t); ov._t=setTimeout(function(){ try{ov.classList.remove('active');}catch(e){ console.warn(\"[가톨릭길동무]\", e); } }, 420); }; })(); (functio"
    },
    {
      "start": 1124,
      "end": 1270,
      "lines": 147,
      "guard": "__APP_PULL_REFRESH_CLEAN_V20_8__",
      "head": "function removeMissaPopupState(){var mv=document.getElementById('missa-view');if(mv&&!document.documentElement.classList.contains('app-active')) mv.classList.remove('open');} if(do"
    },
    {
      "start": 1271,
      "end": 1325,
      "lines": 55,
      "guard": "__APP_TABS_BACK_GUARD__",
      "head": "if(document.readyState === 'loading') document.addEventListener('DOMContentLoaded', installPullRefresh, {once:true}); else installPullRefresh(); })(); (function(){ 'use strict'; if"
    },
    {
      "start": 1326,
      "end": 1469,
      "lines": 144,
      "guard": "__",
      "head": "window.addEventListener('load',function(){boot();setTimeout(boot,200);},{once:true}); pageshow에서 종료 대기값을 지우지 않는다. 커버 진입/복귀 시에는 goToCover와 class 변화 감지에서만 초기화한다. try{new MutationObse"
    }
  ],
  "listeners": [
    {
      "line": 531,
      "target": "window",
      "event": "popstate",
      "code": "window.addEventListener('popstate', function(){"
    },
    {
      "line": 619,
      "target": "document",
      "event": "backbutton",
      "code": "document.addEventListener('backbutton', function(){"
    },
    {
      "line": 635,
      "target": "window",
      "event": "pageshow",
      "code": "window.addEventListener('pageshow', function(){"
    },
    {
      "line": 691,
      "target": "document",
      "event": "click",
      "code": "document.addEventListener('click', function(e){"
    },
    {
      "line": 702,
      "target": "document",
      "event": "DOMContentLoaded",
      "code": "document.addEventListener('DOMContentLoaded', function(){ setTimeout(syncPrayerTabOn, 300); });"
    },
    {
      "line": 703,
      "target": "window",
      "event": "load",
      "code": "window.addEventListener('load', function(){ setTimeout(syncPrayerTabOn, 300); });"
    },
    {
      "line": 710,
      "target": "document",
      "event": "DOMContentLoaded",
      "code": "document.addEventListener('DOMContentLoaded', function(){"
    },
    {
      "line": 752,
      "target": "window",
      "event": "load",
      "code": "window.addEventListener('load',function(){"
    },
    {
      "line": 757,
      "target": "frame",
      "event": "load",
      "code": "frame.addEventListener('load',function(){"
    },
    {
      "line": 763,
      "target": "document",
      "event": "click",
      "code": "document.addEventListener('click',function(){"
    },
    {
      "line": 827,
      "target": "document",
      "event": "DOMContentLoaded",
      "code": "if(document.readyState==='loading') document.addEventListener('DOMContentLoaded', applyScale, {once:true});"
    },
    {
      "line": 829,
      "target": "window",
      "event": "load",
      "code": "window.addEventListener('load', applyScale, {once:true});"
    },
    {
      "line": 867,
      "target": "if(document.readyState==='loading')document",
      "event": "DOMContentLoaded",
      "code": "if(document.readyState==='loading')document.addEventListener('DOMContentLoaded',boot,{once:true});else boot();window.addEventListener('load',function(){boot();s"
    },
    {
      "line": 902,
      "target": "window",
      "event": "beforeinstallprompt",
      "code": "window.addEventListener('beforeinstallprompt', function(e){"
    },
    {
      "line": 911,
      "target": "window",
      "event": "appinstalled",
      "code": "window.addEventListener('appinstalled', function(){"
    },
    {
      "line": 929,
      "target": "standalone)')",
      "event": "change",
      "code": "window.matchMedia('(display-mode: standalone)').addEventListener('change', applyVisibility);"
    },
    {
      "line": 932,
      "target": "window",
      "event": "load",
      "code": "window.addEventListener('load', applyVisibility);"
    },
    {
      "line": 933,
      "target": "window",
      "event": "pageshow",
      "code": "window.addEventListener('pageshow', applyVisibility);"
    },
    {
      "line": 993,
      "target": "el",
      "event": "touchstart",
      "code": "el.addEventListener('touchstart', function(e){"
    },
    {
      "line": 999,
      "target": "el",
      "event": "touchend",
      "code": "el.addEventListener('touchend', function(e){"
    },
    {
      "line": 1081,
      "target": "document",
      "event": "DOMContentLoaded",
      "code": "if(document.readyState==='loading') document.addEventListener('DOMContentLoaded', init); else init();"
    },
    {
      "line": 1082,
      "target": "window",
      "event": "load",
      "code": "window.addEventListener('load', init);"
    },
    {
      "line": 1083,
      "target": "window",
      "event": "pageshow",
      "code": "window.addEventListener('pageshow', init);"
    },
    {
      "line": 1120,
      "target": "document",
      "event": "DOMContentLoaded",
      "code": "if(document.readyState==='loading') document.addEventListener('DOMContentLoaded', removeMissaPopupState, {once:true});"
    },
    {
      "line": 1122,
      "target": "window",
      "event": "pageshow",
      "code": "window.addEventListener('pageshow', removeMissaPopupState);"
    },
    {
      "line": 1219,
      "target": "cover",
      "event": "touchstart",
      "code": "cover.addEventListener('touchstart', function(e){"
    },
    {
      "line": 1228,
      "target": "cover",
      "event": "touchmove",
      "code": "cover.addEventListener('touchmove', function(e){"
    },
    {
      "line": 1253,
      "target": "cover",
      "event": "touchend",
      "code": "cover.addEventListener('touchend', finish, {passive:true, capture:true});"
    },
    {
      "line": 1254,
      "target": "cover",
      "event": "touchcancel",
      "code": "cover.addEventListener('touchcancel', function(){ active=false; ready=false; refreshing=false; hideIndicator(ind); }, {passive:true, capture:true});"
    },
    {
      "line": 1257,
      "target": "window",
      "event": "pageshow",
      "code": "window.addEventListener('pageshow', function(){"
    },
    {
      "line": 1267,
      "target": "document",
      "event": "DOMContentLoaded",
      "code": "if(document.readyState === 'loading') document.addEventListener('DOMContentLoaded', installPullRefresh, {once:true});"
    },
    {
      "line": 1320,
      "target": "if(document.readyState==='loading')document",
      "event": "DOMContentLoaded",
      "code": "if(document.readyState==='loading')document.addEventListener('DOMContentLoaded',boot,{once:true});else boot();"
    },
    {
      "line": 1321,
      "target": "window",
      "event": "load",
      "code": "window.addEventListener('load',function(){boot();setTimeout(boot,200);},{once:true});"
    },
    {
      "line": 1378,
      "target": "document",
      "event": "pointerdown",
      "code": "document.addEventListener('pointerdown', function(e){"
    },
    {
      "line": 1392,
      "target": "document",
      "event": "pointerdown",
      "code": "document.addEventListener('pointerdown', function(e){"
    },
    {
      "line": 1402,
      "target": "document",
      "event": "pointermove",
      "code": "document.addEventListener('pointermove', function(e){"
    },
    {
      "line": 1409,
      "target": "document",
      "event": "pointercancel",
      "code": "document.addEventListener('pointercancel', cancelActive, true);"
    },
    {
      "line": 1410,
      "target": "document",
      "event": "pointerup",
      "code": "document.addEventListener('pointerup', function(e){"
    },
    {
      "line": 1417,
      "target": "document",
      "event": "click",
      "code": "document.addEventListener('click', function(e){"
    },
    {
      "line": 1457,
      "target": "document",
      "event": "DOMContentLoaded",
      "code": "document.addEventListener('DOMContentLoaded', function(){ disableKeyboardSuggestions(document); });"
    }
  ],
  "window_exports": [
    {
      "line": 28,
      "name": "__BACK_CTRL__",
      "code": "window.__BACK_CTRL__ = true;"
    },
    {
      "line": 29,
      "name": "__OAI_FULL_BACK_CTRL_ACTIVE__",
      "code": "window.__OAI_FULL_BACK_CTRL_ACTIVE__ = true;"
    },
    {
      "line": 50,
      "name": "_oaiArmCoverBackTrap",
      "code": "try{ window._oaiArmCoverBackTrap = armCoverBackTrap; }catch(_e){}"
    },
    {
      "line": 75,
      "name": "_isCoverScreenVisible",
      "code": "if(typeof window._isCoverScreenVisible === 'function') return window._isCoverScreenVisible();"
    },
    {
      "line": 85,
      "name": "_isAppScreenActive",
      "code": "try{ if(typeof window._isAppScreenActive === 'function') return window._isAppScreenActive(); }catch(e){}"
    },
    {
      "line": 97,
      "name": "_resetCoverExitReady",
      "code": "if(typeof window._resetCoverExitReady === 'function') window._resetCoverExitReady();"
    },
    {
      "line": 108,
      "name": "closeMyFaithLifeModal",
      "code": "if(typeof window.closeMyFaithLifeModal === 'function' && typeof window.isMyFaithLifeModalOpen === 'function' && window.isMyFaithLifeModalOpen()){"
    },
    {
      "line": 108,
      "name": "isMyFaithLifeModalOpen",
      "code": "if(typeof window.closeMyFaithLifeModal === 'function' && typeof window.isMyFaithLifeModalOpen === 'function' && window.isMyFaithLifeModalOpen()){"
    },
    {
      "line": 112,
      "name": "closeCoverMenuPopup",
      "code": "if(typeof window.closeCoverMenuPopup === 'function' && typeof window.isCoverMenuPopupOpen === 'function' && window.isCoverMenuPopupOpen()){"
    },
    {
      "line": 112,
      "name": "isCoverMenuPopupOpen",
      "code": "if(typeof window.closeCoverMenuPopup === 'function' && typeof window.isCoverMenuPopupOpen === 'function' && window.isCoverMenuPopupOpen()){"
    },
    {
      "line": 117,
      "name": "closeMassQuickMenu",
      "code": "if(mq && mq.classList.contains('show') && typeof window.closeMassQuickMenu === 'function'){"
    },
    {
      "line": 120,
      "name": "_isPrayerPopupReturnSource",
      "code": "try{ if(typeof window._isPrayerPopupReturnSource === 'function' && window._isPrayerPopupReturnSource()) fromPrayer = true; }catch(e){}"
    },
    {
      "line": 131,
      "name": "resetGuideManualScroll",
      "code": "if(typeof window.resetGuideManualScroll === 'function') window.resetGuideManualScroll();"
    },
    {
      "line": 132,
      "name": "_resetCoverExitReady",
      "code": "if(typeof window._resetCoverExitReady === 'function') window._resetCoverExitReady();"
    },
    {
      "line": 137,
      "name": "goToCover",
      "code": "if(typeof window.goToCover === 'function') window.goToCover();"
    },
    {
      "line": 150,
      "name": "closeDioceseView",
      "code": "if(typeof window.closeDioceseView === 'function') window.closeDioceseView();"
    },
    {
      "line": 167,
      "name": "_oaiCloseGeneralModuleToCover",
      "code": "try{ window._oaiCloseGeneralModuleToCover = closeGeneralModuleToCover; }catch(_e){}"
    },
    {
      "line": 177,
      "name": "trailCloseSheet",
      "code": "if(typeof window.trailCloseSheet === 'function') window.trailCloseSheet();"
    },
    {
      "line": 192,
      "name": "closeMissa",
      "code": "if(typeof window.closeMissa === 'function') window.closeMissa();"
    },
    {
      "line": 200,
      "name": "closePrayerView",
      "code": "if(typeof window.closePrayerView === 'function') window.closePrayerView();"
    },
    {
      "line": 216,
      "name": "_closeInfoRouteChoice",
      "code": "if(typeof window._closeInfoRouteChoice==='function') window._closeInfoRouteChoice();"
    },
    {
      "line": 223,
      "name": "closeSearchModal",
      "code": "if(typeof window.closeSearchModal==='function') window.closeSearchModal();"
    },
    {
      "line": 234,
      "name": "resetRoute",
      "code": "try{ if(typeof window.resetRoute==='function') window.resetRoute(); }catch(e){ console.warn(\"[가톨릭길동무]\", e); }"
    },
    {
      "line": 260,
      "name": "closeInfoCard",
      "code": "if(typeof window.closeInfoCard==='function') window.closeInfoCard();"
    },
    {
      "line": 307,
      "name": "__OAI_PRAYER_FROM_QUICK_LOCK__",
      "code": "try{ if(window.__OAI_PRAYER_FROM_QUICK_LOCK__ === true) yes = true; }catch(_e){}"
    },
    {
      "line": 309,
      "name": "_shouldPrayerQuickReturn",
      "code": "try{ if(typeof window._shouldPrayerQuickReturn === 'function' && window._shouldPrayerQuickReturn()) yes = true; }catch(_e){}"
    },
    {
      "line": 313,
      "name": "_setPrayerQuickReturn",
      "code": "try{ if(typeof window._setPrayerQuickReturn === 'function') window._setPrayerQuickReturn(!!on); }catch(_e){}"
    },
    {
      "line": 314,
      "name": "__OAI_PRAYER_FROM_QUICK_LOCK__",
      "code": "try{ window.__OAI_PRAYER_FROM_QUICK_LOCK__ = !!on; }catch(_e){}"
    },
    {
      "line": 329,
      "name": "_isPrayerPopupReturnSource",
      "code": "try{ if(typeof window._isPrayerPopupReturnSource === 'function' && window._isPrayerPopupReturnSource()) yes = true; }catch(_e){}"
    },
    {
      "line": 336,
      "name": "_ensureAppBackTrap",
      "code": "if(isPrayerOpen() && typeof window._ensureAppBackTrap === 'function'){"
    },
    {
      "line": 357,
      "name": "oaiSetMainMapLayerHidden",
      "code": "if(typeof window.oaiSetMainMapLayerHidden === 'function') window.oaiSetMainMapLayerHidden(false);"
    },
    {
      "line": 368,
      "name": "_setPrayerPopupReturnSource",
      "code": "try{ if(typeof window._setPrayerPopupReturnSource === 'function') window._setPrayerPopupReturnSource(false); }catch(_e){}"
    },
    {
      "line": 369,
      "name": "_clearPrayerQuickReturn",
      "code": "try{ if(typeof window._clearPrayerQuickReturn === 'function') window._clearPrayerQuickReturn(); }catch(_e){}"
    },
    {
      "line": 370,
      "name": "_clearMassQuickReturnForReload",
      "code": "try{ if(typeof window._clearMassQuickReturnForReload === 'function') window._clearMassQuickReturnForReload(); }catch(_e){}"
    },
    {
      "line": 371,
      "name": "__OAI_PRAYER_FROM_QUICK_LOCK__",
      "code": "try{ window.__OAI_PRAYER_FROM_QUICK_LOCK__ = false; }catch(_e){}"
    },
    {
      "line": 373,
      "name": "__OAI_PRAYER_POPUP_COVER_GUARD_UNTIL__",
      "code": "try{ window.__OAI_PRAYER_POPUP_COVER_GUARD_UNTIL__ = 0; }catch(_e){}"
    },
    {
      "line": 374,
      "name": "__OAI_PRAYER_COVER_FORCE_FIRST_TOAST_UNTIL__",
      "code": "try{ window.__OAI_PRAYER_COVER_FORCE_FIRST_TOAST_UNTIL__ = 0; }catch(_e){}"
    },
    {
      "line": 378,
      "name": "_resetCoverBackTrap",
      "code": "if(typeof window._resetCoverBackTrap === 'function') window._resetCoverBackTrap(reason || 'prayer-cover-reset');"
    },
    {
      "line": 379,
      "name": "_ensureCoverBackTrap",
      "code": "else if(typeof window._ensureCoverBackTrap === 'function') window._ensureCoverBackTrap(reason || 'prayer-cover-reset');"
    },
    {
      "line": 396,
      "name": "_resetCoverExitReady",
      "code": "if(typeof window._resetCoverExitReady === 'function') window._resetCoverExitReady();"
    },
    {
      "line": 397,
      "name": "_clearCoverExitArmed",
      "code": "if(typeof window._clearCoverExitArmed === 'function') window._clearCoverExitArmed();"
    },
    {
      "line": 398,
      "name": "_ensureCoverBackTrap",
      "code": "if(typeof window._ensureCoverBackTrap === 'function') window._ensureCoverBackTrap((reason||'prayer-cover') + '-' + tag);"
    },
    {
      "line": 421,
      "name": "_resetCoverExitReady",
      "code": "try{ if(typeof window._resetCoverExitReady === 'function') window._resetCoverExitReady(); }catch(_e){}"
    },
    {
      "line": 422,
      "name": "_clearCoverExitArmed",
      "code": "try{ if(typeof window._clearCoverExitArmed === 'function') window._clearCoverExitArmed(); }catch(_e){}"
    },
    {
      "line": 432,
      "name": "prCloseDetail",
      "code": "if(typeof window.prCloseDetail === 'function') window.prCloseDetail({skipTrap:true});"
    },
    {
      "line": 437,
      "name": "showPrayerListOnly",
      "code": "if(typeof window.showPrayerListOnly === 'function') window.showPrayerListOnly();"
    },
    {
      "line": 438,
      "name": "prEnsureTabsVisible",
      "code": "try{ if(typeof window.prEnsureTabsVisible === 'function') window.prEnsureTabsVisible(); }catch(_e){}"
    },
    {
      "line": 455,
      "name": "_setPrayerPopupReturnSource",
      "code": "try{ if(typeof window._setPrayerPopupReturnSource === 'function') window._setPrayerPopupReturnSource(true); }catch(_e){}"
    },
    {
      "line": 456,
      "name": "_resetCoverExitReady",
      "code": "try{ if(typeof window._resetCoverExitReady === 'function') window._resetCoverExitReady(); }catch(_e){}"
    },
    {
      "line": 457,
      "name": "_clearCoverExitArmed",
      "code": "try{ if(typeof window._clearCoverExitArmed === 'function') window._clearCoverExitArmed(); }catch(_e){}"
    },
    {
      "line": 458,
      "name": "_returnToMassQuickMenu",
      "code": "if(typeof window._returnToMassQuickMenu === 'function'){"
    },
    {
      "line": 485,
      "name": "_oaiArmPrayerBackTrap",
      "code": "window._oaiArmPrayerBackTrap = armPrayerBackTrap;"
    },
    {
      "line": 486,
      "name": "_oaiPrayerPushDetailState",
      "code": "window._oaiPrayerPushDetailState = pushPrayerDetailState;"
    },
    {
      "line": 487,
      "name": "_oaiPrayerReplaceListState",
      "code": "window._oaiPrayerReplaceListState = replacePrayerListState;"
    },
    {
      "line": 488,
      "name": "_oaiPrayerBackHandle",
      "code": "window._oaiPrayerBackHandle = handlePrayerBack;"
    },
    {
      "line": 489,
      "name": "_oaiPrayerListToPopupOrCover",
      "code": "window._oaiPrayerListToPopupOrCover = prayerListToPopupOrCover;"
    },
    {
      "line": 490,
      "name": "_oaiPrayerResetToCover",
      "code": "window._oaiPrayerResetToCover = resetPrayerToCover;"
    },
    {
      "line": 499,
      "name": "__OAI_AFTER_RESTORE_PRAYER_QUICK_POPUP__",
      "code": "window.__OAI_AFTER_RESTORE_PRAYER_QUICK_POPUP__ = null;"
    },
    {
      "line": 500,
      "name": "__OAI_AFTER_RESTORE_PRAYER_QUICK_POPUP_UNTIL__",
      "code": "window.__OAI_AFTER_RESTORE_PRAYER_QUICK_POPUP_UNTIL__ = 0;"
    },
    {
      "line": 503,
      "name": "__OAI_AFTER_RESTORE_PRAYER_QUICK_POPUP__",
      "code": "window.__OAI_AFTER_RESTORE_PRAYER_QUICK_POPUP__ = null;"
    },
    {
      "line": 504,
      "name": "__OAI_AFTER_RESTORE_PRAYER_QUICK_POPUP_UNTIL__",
      "code": "window.__OAI_AFTER_RESTORE_PRAYER_QUICK_POPUP_UNTIL__ = 0;"
    },
    {
      "line": 518,
      "name": "__OAI_AFTER_RESTORE_PRAYER_COVER_RESET__",
      "code": "window.__OAI_AFTER_RESTORE_PRAYER_COVER_RESET__ = null;"
    },
    {
      "line": 519,
      "name": "__OAI_AFTER_RESTORE_PRAYER_COVER_RESET_UNTIL__",
      "code": "window.__OAI_AFTER_RESTORE_PRAYER_COVER_RESET_UNTIL__ = 0;"
    },
    {
      "line": 522,
      "name": "__OAI_AFTER_RESTORE_PRAYER_COVER_RESET__",
      "code": "window.__OAI_AFTER_RESTORE_PRAYER_COVER_RESET__ = null;"
    },
    {
      "line": 523,
      "name": "__OAI_AFTER_RESTORE_PRAYER_COVER_RESET_UNTIL__",
      "code": "window.__OAI_AFTER_RESTORE_PRAYER_COVER_RESET_UNTIL__ = 0;"
    },
    {
      "line": 548,
      "name": "__OAI_MQ_STATE_POPPING__",
      "code": "window.__OAI_MQ_STATE_POPPING__ = 0;"
    },
    {
      "line": 550,
      "name": "__OAI_AFTER_MQ_STATE_POP__",
      "code": "window.__OAI_AFTER_MQ_STATE_POP__ = null;"
    },
    {
      "line": 562,
      "name": "__OAI_AFTER_RESTORE_PRAYER_COVER_RESET__",
      "code": "window.__OAI_AFTER_RESTORE_PRAYER_COVER_RESET__ = coverCb;"
    },
    {
      "line": 563,
      "name": "__OAI_AFTER_RESTORE_PRAYER_COVER_RESET_UNTIL__",
      "code": "window.__OAI_AFTER_RESTORE_PRAYER_COVER_RESET_UNTIL__ = Date.now() + 1800;"
    },
    {
      "line": 568,
      "name": "__OAI_AFTER_RESTORE_PRAYER_COVER_RESET__",
      "code": "if(window.__OAI_AFTER_RESTORE_PRAYER_COVER_RESET__ === coverCb){"
    },
    {
      "line": 570,
      "name": "__OAI_AFTER_RESTORE_PRAYER_COVER_RESET__",
      "code": "window.__OAI_AFTER_RESTORE_PRAYER_COVER_RESET__ = null;"
    },
    {
      "line": 571,
      "name": "__OAI_AFTER_RESTORE_PRAYER_COVER_RESET_UNTIL__",
      "code": "window.__OAI_AFTER_RESTORE_PRAYER_COVER_RESET_UNTIL__ = 0;"
    },
    {
      "line": 593,
      "name": "_ensureCoverBackTrap",
      "code": "try{ if(typeof window._ensureCoverBackTrap === 'function') window._ensureCoverBackTrap('guide-modal'); else armCoverBackTrap('guide-modal'); }catch(e){ console."
    },
    {
      "line": 600,
      "name": "_showBackToast",
      "code": "if(typeof window._showBackToast==='function') exiting = window._showBackToast() === true;"
    },
    {
      "line": 624,
      "name": "_showBackToast",
      "code": "if(typeof window._showBackToast==='function') window._showBackToast();"
    },
    {
      "line": 654,
      "name": "__APP_PRAYER_VIEW_HELPER__",
      "code": "window.__APP_PRAYER_VIEW_HELPER__ = true;"
    },
    {
      "line": 665,
      "name": "prRestoreListPosition",
      "code": "if(typeof window.prRestoreListPosition === 'function'){"
    },
    {
      "line": 669,
      "name": "showPrayerListOnly",
      "code": "try{ window.showPrayerListOnly = showPrayerListOnly; }catch(_){ console.warn(\"[가톨릭길동무] silent catch\"); }"
    },
    {
      "line": 677,
      "name": "__APP_PRAYER_SYNC_GUARD__",
      "code": "window.__APP_PRAYER_SYNC_GUARD__ = true;"
    },
    {
      "line": 727,
      "name": "__APP_FAITH_GUARD__",
      "code": "window.__APP_FAITH_GUARD__ = true;"
    },
    {
      "line": 775,
      "name": "__APP_FONT_SCALE_GUARD__",
      "code": "window.__APP_FONT_SCALE_GUARD__=true;"
    },
    {
      "line": 823,
      "name": "__APP_getSharedFontPx",
      "code": "window.__APP_getSharedFontPx=getPx;"
    },
    {
      "line": 824,
      "name": "__APP_setSharedFontPx",
      "code": "window.__APP_setSharedFontPx=setPx;"
    },
    {
      "line": 825,
      "name": "__APP_adjustSharedFont",
      "code": "window.__APP_adjustSharedFont=adjustSharedFont;"
    },
    {
      "line": 826,
      "name": "__APP_applyGlobalFont",
      "code": "window.__APP_applyGlobalFont=applyScale;"
    },
    {
      "line": 849,
      "name": "QNA_FORM_URL",
      "code": "window.QNA_FORM_URL=QA_URL;"
    },
    {
      "line": 853,
      "name": "qnaOpenFormUrl",
      "code": "window.qnaOpenFormUrl=function(){ if(typeof window.goQaFirebase==='function') window.goQaFirebase(); else location.href=QA_URL; };"
    },
    {
      "line": 853,
      "name": "goQaFirebase",
      "code": "window.qnaOpenFormUrl=function(){ if(typeof window.goQaFirebase==='function') window.goQaFirebase(); else location.href=QA_URL; };"
    },
    {
      "line": 859,
      "name": "oaiHoldStabilityVeil",
      "code": "if(typeof window.oaiHoldStabilityVeil === 'function') window.oaiHoldStabilityVeil('qna-open', 1400);"
    },
    {
      "line": 863,
      "name": "openQnaView",
      "code": "window.openQnaView=function(){ goQnaWithLoading(); };"
    },
    {
      "line": 864,
      "name": "goQaFirebase",
      "code": "window.goQaFirebase=function(){ goQnaWithLoading(); };"
    },
    {
      "line": 865,
      "name": "qnaShowTab",
      "code": "window.qnaShowTab=function(){ configureQna(); };"
    },
    {
      "line": 879,
      "name": "__APP_PWA_INSTALL_GUARD__",
      "code": "window.__APP_PWA_INSTALL_GUARD__ = true;"
    },
    {
      "line": 916,
      "name": "triggerPwaInstall",
      "code": "window.triggerPwaInstall = function(){"
    },
    {
      "line": 968,
      "name": "__APP_BACK_ROUTE_GUARD__",
      "code": "window.__APP_BACK_ROUTE_GUARD__ = true;"
    },
    {
      "line": 1009,
      "name": "setWebCat",
      "code": "if(typeof window.setWebCat==='function') window.setWebCat(nextCat);"
    },
    {
      "line": 1012,
      "name": "oaiSwipeAction",
      "code": "if(typeof window.oaiSwipeAction==='function') window.oaiSwipeAction($('web-list'), dx<0?'left':'right');"
    },
    {
      "line": 1052,
      "name": "resetRoute",
      "code": "try{ window.resetRoute = resetRoute; }catch(e){ console.warn(\"[가톨릭길동무]\", e); }"
    },
    {
      "line": 1088,
      "name": "__APP_PRECISE_GUARD__",
      "code": "window.__APP_PRECISE_GUARD__ = true;"
    },
    {
      "line": 1094,
      "name": "oaiResetRouteThenClose",
      "code": "window.oaiResetRouteThenClose=function(){ var dest=rememberRouteDest(); try{ if(typeof window.resetRoute==='function') window.resetRoute(); }catch(e){ console.w"
    },
    {
      "line": 1094,
      "name": "resetRoute",
      "code": "window.oaiResetRouteThenClose=function(){ var dest=rememberRouteDest(); try{ if(typeof window.resetRoute==='function') window.resetRoute(); }catch(e){ console.w"
    },
    {
      "line": 1100,
      "name": "oaiSwipeAction",
      "code": "window.oaiSwipeAction = function(el, dir){"
    },
    {
      "line": 1127,
      "name": "__APP_PULL_REFRESH_CLEAN_V20_8__",
      "code": "window.__APP_PULL_REFRESH_CLEAN_V20_8__ = true;"
    },
    {
      "line": 1154,
      "name": "closeMyFaithLifeModal",
      "code": "if(typeof window.closeMyFaithLifeModal === 'function' && typeof window.isMyFaithLifeModalOpen === 'function' && window.isMyFaithLifeModalOpen()){"
    },
    {
      "line": 1154,
      "name": "isMyFaithLifeModalOpen",
      "code": "if(typeof window.closeMyFaithLifeModal === 'function' && typeof window.isMyFaithLifeModalOpen === 'function' && window.isMyFaithLifeModalOpen()){"
    },
    {
      "line": 1158,
      "name": "closeCoverMenuPopup",
      "code": "if(typeof window.closeCoverMenuPopup === 'function' && typeof window.isCoverMenuPopupOpen === 'function' && window.isCoverMenuPopupOpen()){"
    },
    {
      "line": 1158,
      "name": "isCoverMenuPopupOpen",
      "code": "if(typeof window.closeCoverMenuPopup === 'function' && typeof window.isCoverMenuPopupOpen === 'function' && window.isCoverMenuPopupOpen()){"
    },
    {
      "line": 1163,
      "name": "closeMassQuickMenu",
      "code": "if(mq && mq.classList.contains('show') && typeof window.closeMassQuickMenu === 'function'){"
    },
    {
      "line": 1171,
      "name": "resetGuideManualScroll",
      "code": "if(typeof window.resetGuideManualScroll === 'function') window.resetGuideManualScroll();"
    },
    {
      "line": 1172,
      "name": "_resetCoverExitReady",
      "code": "if(typeof window._resetCoverExitReady === 'function') window._resetCoverExitReady();"
    },
    {
      "line": 1190,
      "name": "__oaiSoftCoverRefresh",
      "code": "window.__oaiSoftCoverRefresh = function(){"
    },
    {
      "line": 1192,
      "name": "_clearMassQuickReturnForReload",
      "code": "try{ if(typeof window._clearMassQuickReturnForReload === 'function') window._clearMassQuickReturnForReload(); }catch(e){ console.warn('[가톨릭길동무]', e); }"
    },
    {
      "line": 1274,
      "name": "__APP_TABS_BACK_GUARD__",
      "code": "window.__APP_TABS_BACK_GUARD__=true;"
    },
    {
      "line": 1288,
      "name": "_exitReady",
      "code": "try{window._exitReady=false; clearTimeout(window._exitTimer);}catch(e){ console.warn(\"[가톨릭길동무]\", e); }"
    },
    {
      "line": 1291,
      "name": "_resetCoverExitReady",
      "code": "if(typeof window._resetCoverExitReady !== 'function') window._resetCoverExitReady = clearNativeExitToast;"
    },
    {
      "line": 1296,
      "name": "_clearCoverExitArmed",
      "code": "try{ if(typeof window._clearCoverExitArmed === 'function') window._clearCoverExitArmed(); }catch(e){ console.warn(\"[가톨릭길동무]\", e); }"
    },
    {
      "line": 1305,
      "name": "goToCover",
      "code": "window.goToCover=function(){"
    },
    {
      "line": 1311,
      "name": "_clearCoverExitArmed",
      "code": "try{ if(typeof window._clearCoverExitArmed === 'function') window._clearCoverExitArmed(); }catch(e){ console.warn(\"[가톨릭길동무]\", e); }"
    },
    {
      "line": 1328,
      "name": "__appTouchUxKeyboard20260506",
      "code": "window.__appTouchUxKeyboard20260506 = true;"
    }
  ],
  "storage_like_keys": [
    "closeExtOrModule-prayer",
    "oai-refresh-content-dialog",
    "oai_prayer_from_quick_lock",
    "oai_refresh_history_compact_reason",
    "oai_refresh_history_compact_until",
    "prayer",
    "prayer-cover",
    "prayer-cover-reset",
    "prayer-detail",
    "prayer-detail-back",
    "prayer-hardware-back",
    "prayer-list",
    "prayer-list-back",
    "prayer-list-cover",
    "prayer-popstate",
    "prayer-popup-cover",
    "prayer-popup-cover-after-restore",
    "prayer-tabs",
    "prayer-ui-state",
    "prayer-view",
    "prayer_font_size",
    "refresh",
    "refresh-dialog-close",
    "refresh-dialog-hardware",
    "refreshing"
  ],
  "category_summary": {
    "A. 뒤로가기·history 핵심 컨트롤러": [
      "25-650 (626줄) guard=__BACK_CTRL__ (function(){ 'use strict'; if(window.__BACK_CTRL__) return; window.__BACK_CTRL__ = true; window.__OAI_FULL_BACK_CTRL_ACTIVE__ = true; var _href = location.href.split('#')[0]; funct",
      "651-674 (24줄) guard=__APP_PRAYER_VIEW_HELPER__ 자동 ?v=Date.now 리디렉션은 사용하지 않음: 버전 문자열과 서비스워커로 캐시를 관리 시작 시 강제 상태 초기화는 사용하지 않음: 뒤로가기와 외부사이트 복귀 상태 보존 (function(){ 'use strict'; if(window.__APP_PRAYER_VIEW_HELPER__) return; window.__"
    ],
    "B. 기도문 복귀/목록 동기화": [
      "675-705 (31줄) guard=__APP_PRAYER_SYNC_GUARD__ })(); (function(){ if(window.__APP_PRAYER_SYNC_GUARD__) return; window.__APP_PRAYER_SYNC_GUARD__ = true; function syncPrayerTabOn(){ var wrap = document.getElementById('prayer-tabs",
      "706-724 (19줄) guard= }, true); document.addEventListener('DOMContentLoaded', function(){ setTimeout(syncPrayerTabOn, 300); }); window.addEventListener('load', function(){ setTimeout(syncPrayerTabOn, 30",
      "773-872 (100줄) guard=__APP_FONT_SCALE_GUARD__ (function(){ if(window.__APP_FONT_SCALE_GUARD__) return; window.__APP_FONT_SCALE_GUARD__=true; V3-13: 커버 글자 크기 조절은 prayer.js에 의존하지 않는 공통 함수가 담당한다. prayer.js는 기도문 화면이 열렸을 때 같은 local",
      "937-964 (28줄) guard= window.addEventListener('load', applyVisibility); window.addEventListener('pageshow', applyVisibility); })(); ====== 성능 최적화 보정 ====== (function(){ 화면 전환 중 불필요한 레이아웃 부담을 줄인다. cover의",
      "1085-1097 (13줄) guard=__APP_PRECISE_GUARD__ } if(document.readyState==='loading') document.addEventListener('DOMContentLoaded', init); else init(); window.addEventListener('load', init); window.addEventListener('pageshow', i",
      "1124-1270 (147줄) guard=__APP_PULL_REFRESH_CLEAN_V20_8__ function removeMissaPopupState(){var mv=document.getElementById('missa-view');if(mv&&!document.documentElement.classList.contains('app-active')) mv.classList.remove('open');} if(do",
      "1326-1469 (144줄) guard=__ window.addEventListener('load',function(){boot();setTimeout(boot,200);},{once:true}); pageshow에서 종료 대기값을 지우지 않는다. 커버 진입/복귀 시에는 goToCover와 class 변화 감지에서만 초기화한다. try{new MutationObse"
    ],
    "C. 커버 글자크기·문의 버튼·설치 버튼": [
      "873-936 (64줄) guard=__APP_PWA_INSTALL_GUARD__ })(); user-cache mode: keep app cache stable; refresh changed files through versioned URLs. ── PWA 설치 버튼 로직 ── (function(){ PWA 설치 버튼 통합 컨트롤러 ① standalone(설치된 앱) 상태이면 버튼 즉시 숨기고 종료 "
    ],
    "D. 스와이프·경로/마커 보강": [
      "965-1084 (120줄) guard=__APP_BACK_ROUTE_GUARD__ if(el) observer.observe(el, {attributes:true, attributeFilter:['class']}); }); })(); (function(){ 'use strict'; if(window.__APP_BACK_ROUTE_GUARD__) return; window.__APP_BACK_ROUTE_",
      "1098-1117 (20줄) guard= function restoreDest(dest){ if(!dest||!dest.lat) return; setTimeout(function(){ try{ var items=(typeof _getCurrentItems==='function')?_getCurrentItems():[]; var idx=(typeof dest.id"
    ],
    "E. 커버 새로고침/종료/보호막 안정화": [
      "1271-1325 (55줄) guard=__APP_TABS_BACK_GUARD__ if(document.readyState === 'loading') document.addEventListener('DOMContentLoaded', installPullRefresh, {once:true}); else installPullRefresh(); })(); (function(){ 'use strict'; if"
    ],
    "F. 성능·터치 피드백 보조": [],
    "G. 확인 후 본 코드 이관 후보": [
      "725-772 (48줄) guard=__APP_FAITH_GUARD__ }).observe(pv, {attributes:true, attributeFilter:['class']}); })(); })(); (function(){ if(window.__APP_FAITH_GUARD__) return; window.__APP_FAITH_GUARD__ = true; function normalizeP",
      "1118-1123 (6줄) guard= ov.classList.add('active'); clearTimeout(ov._t); ov._t=setTimeout(function(){ try{ov.classList.remove('active');}catch(e){ console.warn(\"[가톨릭길동무]\", e); } }, 420); }; })(); (functio"
    ]
  },
  "file_listener_summary": {
    "app.js": {
      "DOMContentLoaded": 7,
      "appinstalled": 1,
      "beforeinstallprompt": 1,
      "blur": 1,
      "click": 11,
      "error": 4,
      "focus": 4,
      "keydown": 2,
      "load": 6,
      "pagehide": 2,
      "pageshow": 7,
      "resize": 2,
      "touchend": 2,
      "touchstart": 1,
      "visibilitychange": 3
    },
    "core.js": {},
    "patches.js": {
      "DOMContentLoaded": 9,
      "appinstalled": 1,
      "backbutton": 1,
      "beforeinstallprompt": 1,
      "change": 1,
      "click": 3,
      "load": 8,
      "pageshow": 6,
      "pointercancel": 1,
      "pointerdown": 2,
      "pointermove": 1,
      "pointerup": 1,
      "popstate": 1,
      "touchcancel": 1,
      "touchend": 2,
      "touchmove": 1,
      "touchstart": 2
    },
    "web.js": {
      "DOMContentLoaded": 1,
      "click": 3,
      "pageshow": 1
    },
    "prayer.js": {
      "click": 2,
      "pageshow": 1,
      "touchcancel": 1,
      "touchend": 2,
      "touchmove": 2,
      "touchstart": 2,
      "visibilitychange": 1
    }
  },
  "duplicate_window_exports": {
    "__APP_adjustSharedFont": [
      "app.js",
      "patches.js",
      "prayer.js"
    ],
    "__APP_applyGlobalFont": [
      "patches.js",
      "prayer.js"
    ],
    "__APP_getSharedFontPx": [
      "patches.js",
      "prayer.js"
    ],
    "__OAI_AFTER_MQ_STATE_POP__": [
      "app.js",
      "patches.js"
    ],
    "__OAI_AFTER_RESTORE_PRAYER_QUICK_POPUP_UNTIL__": [
      "app.js",
      "patches.js"
    ],
    "__OAI_AFTER_RESTORE_PRAYER_QUICK_POPUP__": [
      "app.js",
      "patches.js"
    ],
    "__OAI_MQ_STATE_POPPING__": [
      "app.js",
      "patches.js"
    ],
    "__OAI_PRAYER_COVER_FORCE_FIRST_TOAST_UNTIL__": [
      "app.js",
      "patches.js"
    ],
    "__OAI_PRAYER_FROM_QUICK_LOCK__": [
      "app.js",
      "patches.js"
    ],
    "__OAI_PRAYER_POPUP_COVER_GUARD_UNTIL__": [
      "app.js",
      "patches.js"
    ],
    "__oaiCoverExitUntil": [
      "app.js",
      "core.js"
    ],
    "_appExiting": [
      "app.js",
      "core.js"
    ],
    "_clearCoverExitArmed": [
      "app.js",
      "core.js",
      "patches.js"
    ],
    "_clearMassQuickReturnForReload": [
      "app.js",
      "patches.js"
    ],
    "_clearPrayerQuickReturn": [
      "app.js",
      "patches.js"
    ],
    "_closeInfoRouteChoice": [
      "app.js",
      "patches.js"
    ],
    "_ensureAppBackTrap": [
      "app.js",
      "core.js",
      "patches.js"
    ],
    "_ensureCoverBackTrap": [
      "app.js",
      "core.js",
      "patches.js"
    ],
    "_exitReady": [
      "app.js",
      "core.js",
      "patches.js"
    ],
    "_isAppScreenActive": [
      "app.js",
      "core.js",
      "patches.js"
    ],
    "_isCoverScreenVisible": [
      "app.js",
      "core.js",
      "patches.js"
    ],
    "_isPrayerPopupReturnSource": [
      "app.js",
      "patches.js"
    ],
    "_oaiArmCoverBackTrap": [
      "app.js",
      "patches.js"
    ],
    "_oaiArmPrayerBackTrap": [
      "app.js",
      "patches.js",
      "prayer.js"
    ],
    "_oaiCloseGeneralModuleToCover": [
      "app.js",
      "patches.js"
    ],
    "_oaiPrayerListToPopupOrCover": [
      "app.js",
      "patches.js"
    ],
    "_oaiPrayerPushDetailState": [
      "patches.js",
      "prayer.js"
    ],
    "_oaiPrayerReplaceListState": [
      "patches.js",
      "prayer.js"
    ],
    "_resetAppBackTrap": [
      "app.js",
      "core.js"
    ],
    "_resetCoverBackTrap": [
      "app.js",
      "core.js",
      "patches.js"
    ],
    "_resetCoverExitReady": [
      "app.js",
      "core.js",
      "patches.js",
      "js/myfaith.js"
    ],
    "_returnToMassQuickMenu": [
      "app.js",
      "patches.js"
    ],
    "_setPrayerPopupReturnSource": [
      "app.js",
      "patches.js"
    ],
    "_setPrayerQuickReturn": [
      "app.js",
      "patches.js"
    ],
    "_shouldPrayerQuickReturn": [
      "app.js",
      "patches.js"
    ],
    "_showBackToast": [
      "core.js",
      "patches.js"
    ],
    "closeCoverMenuPopup": [
      "app.js",
      "patches.js",
      "js/myfaith.js"
    ],
    "closeMassQuickMenu": [
      "app.js",
      "patches.js"
    ],
    "closeMyFaithLifeModal": [
      "patches.js",
      "js/myfaith.js"
    ],
    "goToCover": [
      "patches.js",
      "web.js"
    ],
    "initPrayerView": [
      "app.js",
      "prayer.js"
    ],
    "isCoverMenuPopupOpen": [
      "app.js",
      "patches.js"
    ],
    "isMyFaithLifeModalOpen": [
      "patches.js",
      "js/myfaith.js"
    ],
    "oaiHoldStabilityVeil": [
      "app.js",
      "patches.js"
    ],
    "oaiKeepActiveTabsVisible": [
      "app.js",
      "web.js",
      "prayer.js"
    ],
    "oaiResumeMyFaithAfterExternal": [
      "app.js",
      "js/myfaith.js"
    ],
    "oaiSetMainMapLayerHidden": [
      "app.js",
      "patches.js",
      "web.js"
    ],
    "oaiSwipeAction": [
      "app.js",
      "patches.js",
      "prayer.js"
    ],
    "prAdjustFont": [
      "app.js",
      "prayer.js"
    ],
    "prCloseDetail": [
      "app.js",
      "patches.js",
      "prayer.js"
    ],
    "prEnsureTabsVisible": [
      "app.js",
      "patches.js",
      "prayer.js"
    ],
    "prRefreshVisibleCats": [
      "prayer.js",
      "js/myfaith.js"
    ],
    "prRenderList": [
      "app.js",
      "prayer.js"
    ],
    "prRestoreListPosition": [
      "patches.js",
      "prayer.js"
    ],
    "prToggleDetailFav": [
      "app.js",
      "prayer.js"
    ],
    "resetGuideManualScroll": [
      "app.js",
      "patches.js"
    ],
    "setWebCat": [
      "patches.js",
      "web.js"
    ],
    "trailCloseSheet": [
      "patches.js",
      "web.js"
    ]
  }
}